setup.py
easyscrape/__init__.py
easyscrape/easy_parser.py
easyscrape/easy_scrape.py
easyscrape/easy_settings.py
easyscrape/easy_spider.py
easyscrape.egg-info/PKG-INFO
easyscrape.egg-info/SOURCES.txt
easyscrape.egg-info/dependency_links.txt
easyscrape.egg-info/entry_points.txt
easyscrape.egg-info/requires.txt
easyscrape.egg-info/top_level.txt