Metadata-Version: 1.0
Name: easyscrape
Version: 0.23
Summary: Easy to use web scraper
Home-page: https://github.com/xpheal/easyscrape
Author: Wayne Chew
Author-email: xpheal@gmail.com
License: GPL
Platform: UNKNOWN
